mycalc/calculator.py
jungmin_OSS-0.0.1.dist-info/METADATA
jungmin_OSS-0.0.1.dist-info/WHEEL
jungmin_OSS-0.0.1.dist-info/top_level.txt
jungmin_OSS-0.0.1.dist-info/RECORD
